magpy/__init__.py
magpy/backlog_issue.py
magpy/general.py
magpy/hub.py
magpy/hubs.py
magpy/project.py
magpy/projects.py
magpy/sprint.py
magpy/csv_files/__init__.py
magpy/csv_files/backlog_file.py
magpy/csv_files/base.py
magpy/csv_files/event_file.py
magpy/csv_files/sprint_file.py
magpy/events/__init__.py
magpy/events/base.py
magpy/events/label_event.py
magpy/events/project_event.py
magpy/sprint_items/__init__.py
magpy/sprint_items/base.py
magpy/sprint_items/sprint_balance.py
magpy/sprint_items/sprint_issue.py
magpy/sprint_items/sprint_progress.py
magpy_raz-1.0.9.dist-info/LICENSE
magpy_raz-1.0.9.dist-info/METADATA
magpy_raz-1.0.9.dist-info/WHEEL
magpy_raz-1.0.9.dist-info/top_level.txt
magpy_raz-1.0.9.dist-info/RECORD
