Metadata-Version: 2.1
Name: magpy-raz
Version: 1.0.9
Summary: Extract project data from GitLab
Home-page: https://gitlab.com/Razinka/magpy
Author: Raz Nitzan
Author-email: raz.nitzan@gmail.com
License: UNKNOWN
Platform: UNKNOWN
Classifier: Programming Language :: Python :: 3
Classifier: License :: OSI Approved :: MIT License
Classifier: Operating System :: OS Independent
